{
  "generated_at": "2026-05-10T07:21:05.484028+00:00",
  "window_days": 7,
  "report_count": 9,
  "stats": {
    "total": 9,
    "by_type": {
      "trash": {
        "count": 4,
        "max_criticality": 3,
        "top_canals": [
          "Prinsengracht",
          "Grimburgwal",
          "Krom Boomssloot"
        ],
        "examples": [
          "A single e-scooter visible just below the surface.",
          "A single plastic bottle drifting along the embankment.",
          "Shopping cart half-submerged near the bridge piling."
        ]
      },
      "other": {
        "count": 1,
        "max_criticality": 3,
        "top_canals": [
          "Prinsengracht"
        ],
        "examples": [
          "Unusually milky-grey water near a drainage outflow."
        ]
      },
      "blooming": {
        "count": 3,
        "max_criticality": 5,
        "top_canals": [
          "Prinsengracht",
          "Snoekjesgracht",
          "Rokin"
        ],
        "examples": [
          "Surface entirely covered in green-blue scum — full bloom.",
          "Dense surface mat covering roughly a third of the visible water.",
          "Patches of greenish water near the houseboat moorings."
        ]
      },
      "petroleum": {
        "count": 1,
        "max_criticality": 2,
        "top_canals": [
          "Prinsengracht"
        ],
        "examples": [
          "Iridescent rainbow sheen across a moderate area near a moored boat."
        ]
      }
    },
    "top_canals": [
      {
        "name": "Prinsengracht",
        "count": 4
      },
      {
        "name": "Grimburgwal",
        "count": 1
      },
      {
        "name": "Krom Boomssloot",
        "count": 1
      },
      {
        "name": "Snoekjesgracht",
        "count": 1
      },
      {
        "name": "Keizersgracht",
        "count": 1
      }
    ]
  },
  "trend": {
    "current": 9,
    "prior": 0,
    "delta": 9
  },
  "narrative": {
    "intro": "<p>Nine approved reports this week, up from zero the previous period. The dominant pattern is a mix of surface issues on the <strong>Prinsengracht</strong>, alongside some significant blooming activity across several canals.</p>",
    "by_type": {
      "trash": "<p>Reports from the <strong>Prinsengracht</strong>, <strong>Grimburgwal</strong>, and <strong>Krom Boomssloot</strong> described a mix of small litter like plastic bottles and larger submerged objects such as e-scooters and a shopping cart. These were mostly minor to moderate incidents.</p>",
      "other": "<p>One report from the <strong>Prinsengracht</strong> noted unusually milky-grey water near a drainage outflow, a concerning observation that warrants attention.</p>",
      "blooming": "<p>Reports from the <strong>Prinsengracht</strong>, <strong>Snoekjesgracht</strong>, and <strong>Rokin</strong> described dense green-blue scum and surface mats, with one case being a severe full bloom.</p>",
      "petroleum": "<p>A single iridescent rainbow sheen was reported on the <strong>Prinsengracht</strong>, which appears to be a minor incident.</p>"
    },
    "outlook": "<p>Temperatures remain cool, with highs only reaching 15.9 °C and rainfall occurring on several days. These conditions should slow or pause the blooming activity reported on the <strong>Prinsengracht</strong>, <strong>Snoekjesgracht</strong>, and <strong>Rokin</strong>.</p>",
    "thanks": "<p>Thank you to the nine citizens who shared their photos this week. Your vigilance helps us see what's happening in the water. To everyone reading: if you spot something unusual, please send us your next report. 💧</p>"
  }
}